booosta_proto/__init__.py
booosta_proto/app.py
booosta_proto/permissions.py
booosta_proto/utils.py
booosta_proto/proto/__init__.py
booosta_proto/py_grpc/__init__.py
booosta_proto/py_grpc/inventory_pb2.py
booosta_proto/py_grpc/inventory_pb2_grpc.py
booosta_proto/py_grpc/order_pb2.py
booosta_proto/py_grpc/order_pb2_grpc.py
booosta_proto/py_grpc/payment_pb2.py
booosta_proto/py_grpc/payment_pb2_grpc.py
booosta_proto/py_grpc/personnel_pb2.py
booosta_proto/py_grpc/personnel_pb2_grpc.py
booosta_proto/py_grpc/user_pb2.py
booosta_proto/py_grpc/user_pb2_grpc.py
booosta_proto-0.0.7.dist-info/METADATA
booosta_proto-0.0.7.dist-info/WHEEL
booosta_proto-0.0.7.dist-info/entry_points.txt
booosta_proto-0.0.7.dist-info/top_level.txt
booosta_proto-0.0.7.dist-info/RECORD
