Metadata-Version: 2.1
Name: booosta-proto
Version: 0.0.7
Summary: gRPC Proto for Test Booosta.
Home-page: https://github.com/Prunedge-Dev-Team/booosta-proto
Project-URL: Bug Tracker, https://github.com/Prunedge-Dev-Team/booosta-proto/issues
Project-URL: Changelog, https://github.com/Prunedge-Dev-Team/booosta-proto/releases
Classifier: Development Status :: 4 - Beta
Classifier: Intended Audience :: Developers
Classifier: License :: OSI Approved :: Apache Software License
Classifier: Programming Language :: Python
Classifier: Programming Language :: Python :: 3
Classifier: Programming Language :: Python :: 3.10
Classifier: Programming Language :: Python :: 3.11
Classifier: Programming Language :: Python :: 3 :: Only
Classifier: License :: OSI Approved :: BSD License
Classifier: Intended Audience :: Developers
Requires-Python: >=3.6
